hpe_storage_flowkit/README.md
hpe_storage_flowkit/docs/README.md
hpe_storage_flowkit/src/__init__.py
hpe_storage_flowkit/src/cinder_client.py
hpe_storage_flowkit/src/core/__init__.py
hpe_storage_flowkit/src/core/example_rest_client_usage.py
hpe_storage_flowkit/src/core/example_session_usage.py
hpe_storage_flowkit/src/core/example_usage.py
hpe_storage_flowkit/src/core/exceptions.py
hpe_storage_flowkit/src/core/rest_client.py
hpe_storage_flowkit/src/core/session.py
hpe_storage_flowkit/src/core/showport_parser.py
hpe_storage_flowkit/src/core/ssh.py
hpe_storage_flowkit/src/utils/clone_utils.py
hpe_storage_flowkit/src/utils/cpg_utils.py
hpe_storage_flowkit/src/utils/host_utils.py
hpe_storage_flowkit/src/utils/hostset_utils.py
hpe_storage_flowkit/src/utils/qos_utils.py
hpe_storage_flowkit/src/utils/remote_copy_utils.py
hpe_storage_flowkit/src/utils/schedule_utils.py
hpe_storage_flowkit/src/utils/snapshot_utils.py
hpe_storage_flowkit/src/utils/task_utils.py
hpe_storage_flowkit/src/utils/utils.py
hpe_storage_flowkit/src/utils/vlun_utils.py
hpe_storage_flowkit/src/utils/volume_utils.py
hpe_storage_flowkit/src/utils/volumeset_utils.py
hpe_storage_flowkit/src/validators/__init__.py
hpe_storage_flowkit/src/validators/cpg_validator.py
hpe_storage_flowkit/src/validators/host_validator.py
hpe_storage_flowkit/src/validators/hostset_validator.py
hpe_storage_flowkit/src/validators/qos_validator.py
hpe_storage_flowkit/src/validators/remote_copy_validator.py
hpe_storage_flowkit/src/validators/snapshot_validator.py
hpe_storage_flowkit/src/validators/vlun_validator.py
hpe_storage_flowkit/src/validators/volume_validator.py
hpe_storage_flowkit/src/validators/volumeset_validator.py
hpe_storage_flowkit/src/workflows/__init__.py
hpe_storage_flowkit/src/workflows/clone.py
hpe_storage_flowkit/src/workflows/cpg.py
hpe_storage_flowkit/src/workflows/host.py
hpe_storage_flowkit/src/workflows/hostset.py
hpe_storage_flowkit/src/workflows/qos.py
hpe_storage_flowkit/src/workflows/remote_copy.py
hpe_storage_flowkit-0.1.dist-info/METADATA
hpe_storage_flowkit-0.1.dist-info/WHEEL
hpe_storage_flowkit-0.1.dist-info/licenses/LICENSE
hpe_storage_flowkit-0.1.dist-info/RECORD
