Metadata-Version: 2.4
Name: hpe_storage_flowkit
Version: 0.1
Summary: HPE Alletra MP REST Client
Author-email: Raghavendra Tilay <raghavendra-uddhav.tilay@hpe.com>
License-File: LICENSE
Classifier: Development Status :: 5 - Production/Stable
Classifier: Environment :: Web Environment
Classifier: Intended Audience :: Developers
Classifier: License :: OSI Approved :: Apache Software License
Classifier: Operating System :: OS Independent
Classifier: Programming Language :: Python
Classifier: Programming Language :: Python :: 3.12
Classifier: Topic :: Internet :: WWW/HTTP
